{
  "asset": {
    "version": "1.1"
  },
  "geometricError": 30.0,
  "root": {
    "boundingVolume": {
      "box": [
        0.0,
        -0.5464500000234693,
        36.05,
        552.164059999981,
        0.0,
        0.0,
        0.0,
        373.82770000002347,
        0.0,
        0.0,
        0.0,
        40.45
      ]
    },
    "geometricError": 30.0,
    "refine": "REPLACE",
    "content": {
      "boundingVolume": {
        "box": [
          68.9704100000672,
          -1.9869550000876188,
          36.05,
          474.5110899999854,
          0.0,
          0.0,
          0.0,
          372.3871950000175,
          0.0,
          0.0,
          0.0,
          40.45
        ]
      },
      "uri": "6/37/61.glb"
    },
    "children": [
      {
        "boundingVolume": {
          "box": [
            3.4771600000094622,
            0.0,
            17.0500002,
            279.55918999999994,
            0.0,
            0.0,
            0.0,
            186.64061999996193,
            0.0,
            0.0,
            0.0,
            12.9499998
          ]
        },
        "geometricError": 10.0,
        "refine": "REPLACE",
        "transform": [
          0.9999999989023142,
          -1.7866736698485264e-05,
          4.3314561198992685e-05,
          0.0,
          1.7865469090216912e-05,
          0.9999999994121809,
          2.9265386378929392e-05,
          0.0,
          -4.3315084050532526e-05,
          -2.9264612511792354e-05,
          0.9999999986336929,
          0.0,
          -276.1342917904258,
          -186.56233105878346,
          0.43407196970656514,
          1.0
        ],
        "content": {
          "boundingVolume": {
            "box": [
              219.95063999993727,
              -120.50012700003572,
              17.0500002,
              63.085709999955725,
              0.0,
              0.0,
              0.0,
              64.1070029999828,
              0.0,
              0.0,
              0.0,
              12.9499998
            ]
          },
          "uri": "7/74/122.glb"
        }
      },
      {
        "boundingVolume": {
          "box": [
            -0.15984999993816018,
            -0.5464500000234693,
            6.999999999999999,
            276.24188000004506,
            0.0,
            0.0,
            0.0,
            187.1870699999854,
            0.0,
            0.0,
            0.0,
            11.399999999999999
          ]
        },
        "geometricError": 10.0,
        "refine": "REPLACE",
        "transform": [
          0.9999999989031488,
          1.7859944027837082e-05,
          -4.3298093639565494e-05,
          0.0,
          -1.7858675846971206e-05,
          0.999999999411589,
          2.9289741742100084e-05,
          0.0,
          4.329861672719426e-05,
          -2.9288968463325737e-05,
          0.9999999986336932,
          0.0,
          276.0293123801239,
          -186.7176006147638,
          0.4344404637813568,
          1.0
        ],
        "content": {
          "boundingVolume": {
            "box": [
              -4.501124999951571,
              -19.946824999991804,
              6.999999999999999,
              271.90060500003165,
              0.0,
              0.0,
              0.0,
              167.78669500001706,
              0.0,
              0.0,
              0.0,
              11.399999999999999
            ]
          },
          "uri": "7/75/122.glb"
        }
      },
      {
        "boundingVolume": {
          "box": [
            0.0,
            0.0,
            49.0,
            276.0820300000487,
            0.0,
            0.0,
            0.0,
            186.64061999996193,
            0.0,
            0.0,
            0.0,
            27.5
          ]
        },
        "geometricError": 10.0,
        "refine": "REPLACE",
        "transform": [
          0.9999999989030954,
          -1.7860378358436346e-05,
          4.3299146592845617e-05,
          0.0,
          1.7861646521344365e-05,
          0.9999999994115814,
          -2.9288194318188854e-05,
          0.0,
          -4.329862346919011e-05,
          2.9288967680174416e-05,
          0.9999999986336929,
          0.0,
          -276.02931698411703,
          186.71756966318935,
          -0.4518752247095108,
          1.0
        ],
        "content": {
          "boundingVolume": {
            "box": [
              -117.62565300008282,
              128.24993199994788,
              49.0,
              11.832997000019532,
              0.0,
              0.0,
              0.0,
              55.509697999979835,
              0.0,
              0.0,
              0.0,
              27.5
            ]
          },
          "uri": "7/74/123.glb"
        }
      },
      {
        "boundingVolume": {
          "box": [
            0.0,
            0.0,
            9.0000002,
            276.0820300000487,
            0.0,
            0.0,
            0.0,
            186.64061999996193,
            0.0,
            0.0,
            0.0,
            5.8999998
          ]
        },
        "geometricError": 10.0,
        "refine": "REPLACE",
        "transform": [
          0.999999998902261,
          1.786717028404161e-05,
          -4.331561234610648e-05,
          0.0,
          -1.7868437874102305e-05,
          0.9999999994121732,
          -2.9263834454729132e-05,
          0.0,
          4.3315089458650924e-05,
          2.9264608404966364e-05,
          0.999999998633693,
          0.0,
          276.1342879086733,
          186.56227896129712,
          -0.4515066300518811,
          1.0
        ],
        "content": {
          "boundingVolume": {
            "box": [
              -17.535719500039704,
              -182.33987500006333,
              9.0000002,
              2.162000500014983,
              0.0,
              0.0,
              0.0,
              1.8325049999984913,
              0.0,
              0.0,
              0.0,
              5.8999998
            ]
          },
          "uri": "7/75/123.glb"
        }
      }
    ]
  }
}