{
  "asset": {
    "version": "1.1"
  },
  "geometricError": 30.0,
  "root": {
    "boundingVolume": {
      "box": [
        0.0,
        5.352925000013784,
        52.1,
        552.164059999981,
        0.0,
        0.0,
        0.0,
        378.6341750000138,
        0.0,
        0.0,
        0.0,
        59.800000000000004
      ]
    },
    "geometricError": 30.0,
    "refine": "REPLACE",
    "content": {
      "boundingVolume": {
        "box": [
          71.86611000006087,
          27.181540000019595,
          52.1,
          414.563909999968,
          0.0,
          0.0,
          0.0,
          356.805560000008,
          0.0,
          0.0,
          0.0,
          59.800000000000004
        ]
      },
      "uri": "6/22/31.glb"
    },
    "children": [
      {
        "boundingVolume": {
          "box": [
            0.9832599998917431,
            1.2106250000651926,
            18.1,
            277.06528999999864,
            0.0,
            0.0,
            0.0,
            187.8512449999689,
            0.0,
            0.0,
            0.0,
            25.0
          ]
        },
        "geometricError": 10.0,
        "refine": "REPLACE",
        "transform": [
          0.9999999989070807,
          -1.7675920908788445e-05,
          4.3282789800980215e-05,
          0.0,
          1.7674652238119926e-05,
          0.999999999414224,
          2.931141108830637e-05,
          0.0,
          -4.328330788183621e-05,
          -2.9310646048053002e-05,
          0.9999999986337206,
          0.0,
          -275.93401125073433,
          -186.85734829842113,
          0.43163327453657985,
          1.0
        ],
        "content": {
          "boundingVolume": {
            "box": [
              106.36409000004642,
              79.69836799998302,
              18.1,
              171.68445999996038,
              0.0,
              0.0,
              0.0,
              109.36350199999288,
              0.0,
              0.0,
              0.0,
              25.0
            ]
          },
          "uri": "7/44/62.glb"
        }
      },
      {
        "boundingVolume": {
          "box": [
            -1.7779999999329448,
            2.0694900000235066,
            18.75,
            277.86003000003984,
            0.0,
            0.0,
            0.0,
            188.71010999998543,
            0.0,
            0.0,
            0.0,
            24.950000000000003
          ]
        },
        "geometricError": 10.0,
        "refine": "REPLACE",
        "transform": [
          0.9999999989047468,
          1.769478375773792e-05,
          -4.332897900555244e-05,
          0.0,
          -1.769351669322905e-05,
          0.9999999994158905,
          2.9243097848019595e-05,
          0.0,
          4.332949643054418e-05,
          -2.9242331173962022e-05,
          0.9999999986337202,
          0.0,
          276.22846632264555,
          -186.42183633195236,
          0.43060701340436935,
          1.0
        ],
        "content": {
          "boundingVolume": {
            "box": [
              -34.92773500003386,
              23.505385000025854,
              18.75,
              244.71029499999713,
              0.0,
              0.0,
              0.0,
              167.2742149999831,
              0.0,
              0.0,
              0.0,
              24.950000000000003
            ]
          },
          "uri": "7/45/62.glb"
        }
      },
      {
        "boundingVolume": {
          "box": [
            2.317520000040531,
            -2.631000000052154,
            11.75,
            278.399550000031,
            0.0,
            0.0,
            0.0,
            189.27161999995587,
            0.0,
            0.0,
            0.0,
            16.05
          ]
        },
        "geometricError": 10.0,
        "refine": "REPLACE",
        "transform": [
          0.9999999989046943,
          -1.769520803429625e-05,
          4.333001792583557e-05,
          0.0,
          1.7696475080569707e-05,
          0.9999999994158831,
          -2.9241557026382647e-05,
          0.0,
          -4.332950046515016e-05,
          2.924232378292979e-05,
          0.9999999986337205,
          0.0,
          -276.2284539733082,
          186.42176351929083,
          -0.4480417505837977,
          1.0
        ],
        "content": {
          "boundingVolume": {
            "box": [
              107.05064500006847,
              -40.64126499998383,
              11.75,
              173.66642500000307,
              0.0,
              0.0,
              0.0,
              151.261354999966,
              0.0,
              0.0,
              0.0,
              16.05
            ]
          },
          "uri": "7/44/63.glb"
        }
      },
      {
        "boundingVolume": {
          "box": [
            -1.0551599999889731,
            -26.78551499999594,
            52.1,
            277.13719000003766,
            0.0,
            0.0,
            0.0,
            224.13196499994956,
            0.0,
            0.0,
            0.0,
            59.800000000000004
          ]
        },
        "geometricError": 10.0,
        "refine": "REPLACE",
        "transform": [
          0.9999999989070281,
          1.767634735011514e-05,
          -4.3283834022134204e-05,
          0.0,
          -1.7677616003242136e-05,
          0.9999999994142166,
          -2.9309883463668474e-05,
          0.0,
          4.328331590508494e-05,
          2.931064858663346e-05,
          0.9999999986337202,
          0.0,
          275.9340242790058,
          186.85733866714872,
          -0.4490683078765869,
          1.0
        ],
        "content": {
          "boundingVolume": {
            "box": [
              -33.922179999994114,
              -26.78551499999594,
              52.1,
              244.27017000003252,
              0.0,
              0.0,
              0.0,
              224.13196499994956,
              0.0,
              0.0,
              0.0,
              59.800000000000004
            ]
          },
          "uri": "7/45/63.glb"
        }
      }
    ]
  }
}