{
  "asset": {
    "version": "1.1"
  },
  "geometricError": 30.0,
  "root": {
    "boundingVolume": {
      "box": [
        0.0,
        -7.229659999953583,
        27.45,
        552.164059999981,
        0.0,
        0.0,
        0.0,
        380.5109100000118,
        0.0,
        0.0,
        0.0,
        32.65
      ]
    },
    "geometricError": 30.0,
    "refine": "REPLACE",
    "content": {
      "boundingVolume": {
        "box": [
          -241.88861900009215,
          -162.2571600000374,
          27.45,
          305.6576810000115,
          0.0,
          0.0,
          0.0,
          225.48340999998618,
          0.0,
          0.0,
          0.0,
          32.65
        ]
      },
      "uri": "6/39/21.glb"
    },
    "children": [
      {
        "boundingVolume": {
          "box": [
            5.545034999959171,
            -7.342355000087991,
            27.45,
            281.62706500000786,
            0.0,
            0.0,
            0.0,
            193.9829749999917,
            0.0,
            0.0,
            0.0,
            32.65
          ]
        },
        "geometricError": 10.0,
        "refine": "REPLACE",
        "transform": [
          0.9999999989063405,
          -1.7631215164543024e-05,
          4.331811692309673e-05,
          0.0,
          1.7629947726388595e-05,
          0.9999999994165465,
          2.9259055247143895e-05,
          0.0,
          -4.331863277040604e-05,
          -2.9258291518952095e-05,
          0.999999998633724,
          0.0,
          -276.1599705880508,
          -186.52409849036485,
          0.4297993606887758,
          1.0
        ],
        "content": {
          "boundingVolume": {
            "box": [
              7.853889999911189,
              -13.989225000026636,
              27.45,
              279.31820999999763,
              0.0,
              0.0,
              0.0,
              187.33610499999486,
              0.0,
              0.0,
              0.0,
              32.65
            ]
          },
          "uri": "7/78/42.glb"
        }
      },
      {
        "boundingVolume": {
          "box": [
            -6.945464999997057,
            -6.122255000052974,
            27.15,
            283.02749500004575,
            0.0,
            0.0,
            0.0,
            192.7628749999567,
            0.0,
            0.0,
            0.0,
            32.25
          ]
        },
        "geometricError": 10.0,
        "refine": "REPLACE",
        "transform": [
          0.9999999989075805,
          1.762121815640505e-05,
          -4.329355528248646e-05,
          0.0,
          -1.7619949864128293e-05,
          0.9999999994156589,
          2.9295381632044037e-05,
          0.0,
          4.329407147757314e-05,
          -2.9294618769770686e-05,
          0.999999998633724,
          0.0,
          276.00339027959853,
          -186.75568782212213,
          0.4303437846247107,
          1.0
        ],
        "content": {
          "boundingVolume": {
            "box": [
              -251.14296500000637,
              -162.73662999994121,
              27.15,
              38.82999500003643,
              0.0,
              0.0,
              0.0,
              36.14849999995204,
              0.0,
              0.0,
              0.0,
              32.25
            ]
          },
          "uri": "7/79/42.glb"
        }
      },
      {
        "boundingVolume": {
          "box": [
            0.0,
            0.0,
            41.55,
            276.0820300000487,
            0.0,
            0.0,
            0.0,
            186.64061999996193,
            0.0,
            0.0,
            0.0,
            9.45
          ]
        },
        "geometricError": 10.0,
        "refine": "REPLACE",
        "transform": [
          0.9999999989075281,
          -1.762164123639276e-05,
          4.3294594747445014e-05,
          0.0,
          1.7622909510989215e-05,
          0.9999999994156517,
          -2.929385594879763e-05,
          0.0,
          -4.329407851627609e-05,
          2.929461889344953e-05,
          0.9999999986337238,
          0.0,
          -276.00339713459834,
          186.75566288619302,
          -0.4477788817603141,
          1.0
        ],
        "content": {
          "boundingVolume": {
            "box": [
              -231.13171999994665,
              -150.4893775000237,
              41.55,
              18.76718999998411,
              0.0,
              0.0,
              0.0,
              27.07500249997247,
              0.0,
              0.0,
              0.0,
              9.45
            ]
          },
          "uri": "7/78/43.glb"
        }
      }
    ]
  }
}