{
  "asset": {
    "version": "1.1"
  },
  "geometricError": 30.0,
  "root": {
    "boundingVolume": {
      "box": [
        -7.119249999988824,
        10.38675000006333,
        70.55,
        585.4280499999877,
        0.0,
        0.0,
        0.0,
        383.6680000000051,
        0.0,
        0.0,
        0.0,
        77.35000000000001
      ]
    },
    "geometricError": 30.0,
    "refine": "REPLACE",
    "content": {
      "boundingVolume": {
        "box": [
          -7.119249999988824,
          30.770075000007637,
          70.55,
          585.4280499999877,
          0.0,
          0.0,
          0.0,
          363.2846750000026,
          0.0,
          0.0,
          0.0,
          77.35000000000001
        ]
      },
      "uri": "6/34/24.glb"
    },
    "children": [
      {
        "boundingVolume": {
          "box": [
            1.9566499999491498,
            1.8037050000857562,
            29.35,
            278.03867999999784,
            0.0,
            0.0,
            0.0,
            188.44432499998948,
            0.0,
            0.0,
            0.0,
            35.65
          ]
        },
        "geometricError": 10.0,
        "refine": "REPLACE",
        "transform": [
          0.9999999989065486,
          -1.7644763477875358e-05,
          4.3307797594260844e-05,
          0.0,
          1.7643495675012666e-05,
          0.9999999994158566,
          2.927444902445231e-05,
          0.0,
          -4.3308314109813395e-05,
          -2.9273684891528706e-05,
          0.9999999986337207,
          0.0,
          -276.0939600151032,
          -186.6220782797318,
          0.43034502072259784,
          1.0
        ],
        "content": {
          "boundingVolume": {
            "box": [
              13.061819999944419,
              22.18703499995172,
              29.35,
              266.93351000000257,
              0.0,
              0.0,
              0.0,
              168.0609950000071,
              0.0,
              0.0,
              0.0,
              35.65
            ]
          },
          "uri": "7/68/48.glb"
        }
      },
      {
        "boundingVolume": {
          "box": [
            0.0,
            0.9693100000731647,
            49.550000000000004,
            276.0820300000487,
            0.0,
            0.0,
            0.0,
            187.60992999997688,
            0.0,
            0.0,
            0.0,
            55.85
          ]
        },
        "geometricError": 10.0,
        "refine": "REPLACE",
        "transform": [
          0.9999999989067403,
          1.764321453243123e-05,
          -4.330399581947697e-05,
          0.0,
          -1.7641946597285463e-05,
          0.9999999994157194,
          2.928007182934067e-05,
          0.0,
          4.3304512388708805e-05,
          -2.927930783053201e-05,
          0.9999999986337207,
          0.0,
          276.06972374301404,
          -186.65792496711947,
          0.43042934965342283,
          1.0
        ],
        "content": {
          "boundingVolume": {
            "box": [
              -19.919149999972433,
              76.37797799997497,
              49.550000000000004,
              249.79594999999972,
              0.0,
              0.0,
              0.0,
              112.20126200001687,
              0.0,
              0.0,
              0.0,
              55.85
            ]
          },
          "uri": "7/69/48.glb"
        }
      },
      {
        "boundingVolume": {
          "box": [
            -1.1925500000361353,
            -107.27744000009261,
            70.8,
            315.2727200000081,
            0.0,
            0.0,
            0.0,
            309.2224399999832,
            0.0,
            0.0,
            0.0,
            77.10000000000001
          ]
        },
        "geometricError": 10.0,
        "refine": "REPLACE",
        "transform": [
          0.9999999989066878,
          -1.7643637984343652e-05,
          4.330503515165285e-05,
          0.0,
          1.7644905901670338e-05,
          0.9999999994157122,
          -2.9278541661292845e-05,
          0.0,
          -4.330451854656081e-05,
          2.9279305742424544e-05,
          0.9999999986337205,
          0.0,
          -276.0697249658406,
          186.65788593911566,
          -0.44786436832509935,
          1.0
        ],
        "content": {
          "boundingVolume": {
            "box": [
              -1.1925500000361353,
              -107.27744000009261,
              70.8,
              315.2727200000081,
              0.0,
              0.0,
              0.0,
              309.2224399999832,
              0.0,
              0.0,
              0.0,
              77.10000000000001
            ]
          },
          "uri": "7/68/49.glb"
        }
      },
      {
        "boundingVolume": {
          "box": [
            -13.388789999997243,
            -2.1688800000119954,
            50.15,
            315.615540000028,
            0.0,
            0.0,
            0.0,
            209.58299999998417,
            0.0,
            0.0,
            0.0,
            56.949999999999996
          ]
        },
        "geometricError": 10.0,
        "refine": "REPLACE",
        "transform": [
          0.9999999989064959,
          1.764518677616067e-05,
          -4.330883654929396e-05,
          0.0,
          -1.7646454561148772e-05,
          0.9999999994158493,
          -2.9272917915157404e-05,
          0.0,
          4.330831999771467e-05,
          2.9273682130459555e-05,
          0.9999999986337206,
          0.0,
          276.0939595210366,
          186.6220349711366,
          -0.4477800165768713,
          1.0
        ],
        "content": {
          "boundingVolume": {
            "box": [
              -13.388789999997243,
              -2.1688800000119954,
              50.15,
              315.615540000028,
              0.0,
              0.0,
              0.0,
              209.58299999998417,
              0.0,
              0.0,
              0.0,
              56.949999999999996
            ]
          },
          "uri": "7/69/49.glb"
        }
      }
    ]
  }
}