{
  "asset": {
    "version": "1.1"
  },
  "geometricError": 30.0,
  "root": {
    "boundingVolume": {
      "box": [
        0.0,
        0.0,
        1.5499999999999998,
        552.164059999981,
        0.0,
        0.0,
        0.0,
        373.28125,
        0.0,
        0.0,
        0.0,
        7.05
      ]
    },
    "geometricError": 30.0,
    "refine": "REPLACE",
    "content": {
      "boundingVolume": {
        "box": [
          296.95405499998014,
          -50.76124999998137,
          1.5499999999999998,
          3.2834949999814853,
          0.0,
          0.0,
          0.0,
          3.4294999999692664,
          0.0,
          0.0,
          0.0,
          7.05
        ]
      },
      "uri": "6/43/43.glb"
    },
    "children": [
      {
        "boundingVolume": {
          "box": [
            0.0,
            0.0,
            1.5499999999999998,
            276.0820300000487,
            0.0,
            0.0,
            0.0,
            186.64061999996193,
            0.0,
            0.0,
            0.0,
            7.05
          ]
        },
        "geometricError": 10.0,
        "refine": "REPLACE",
        "transform": [
          0.9999999989056954,
          1.7747972622356167e-05,
          -4.328531412867154e-05,
          0.0,
          -1.7746704023657855e-05,
          0.9999999994130464,
          2.9308038984654505e-05,
          0.0,
          4.328583426127519e-05,
          -2.930727078098716e-05,
          0.9999999986337105,
          0.0,
          275.9492018772289,
          -186.8352110851556,
          0.432839032728225,
          1.0
        ],
        "content": {
          "boundingVolume": {
            "box": [
              20.872030499973334,
              135.87936999998055,
              1.5499999999999998,
              3.2834995000157505,
              0.0,
              0.0,
              0.0,
              3.4294999999692664,
              0.0,
              0.0,
              0.0,
              7.05
            ]
          },
          "uri": "7/87/86.glb"
        }
      }
    ]
  }
}