{
  "asset": {
    "version": "1.1"
  },
  "geometricError": 30.0,
  "root": {
    "boundingVolume": {
      "box": [
        -3.203250000020489,
        0.0,
        6.9,
        555.3673100000015,
        0.0,
        0.0,
        0.0,
        373.28125,
        0.0,
        0.0,
        0.0,
        13.700000000000001
      ]
    },
    "geometricError": 30.0,
    "refine": "REPLACE",
    "content": {
      "boundingVolume": {
        "box": [
          -495.27505500009283,
          -132.80975500005297,
          6.9,
          63.295504999987315,
          0.0,
          0.0,
          0.0,
          143.34200500004226,
          0.0,
          0.0,
          0.0,
          13.700000000000001
        ]
      },
      "uri": "6/44/45.glb"
    },
    "children": [
      {
        "boundingVolume": {
          "box": [
            -3.203250000020489,
            1.9251300001051277,
            6.9,
            279.28528000001097,
            0.0,
            0.0,
            0.0,
            188.56575000000885,
            0.0,
            0.0,
            0.0,
            13.700000000000001
          ]
        },
        "geometricError": 10.0,
        "refine": "REPLACE",
        "transform": [
          0.9999999989032801,
          -1.7777693176762588e-05,
          4.332890109387533e-05,
          0.0,
          1.7776426093074615e-05,
          0.9999999994144053,
          2.9243592566008392e-05,
          0.0,
          -4.332942095208736e-05,
          -2.9242822300934446e-05,
          0.9999999986337095,
          0.0,
          -276.2269161688164,
          -186.42424585367553,
          0.43207656824961305,
          1.0
        ],
        "content": {
          "boundingVolume": {
            "box": [
              -219.19303500000387,
              50.48988000000827,
              6.9,
              63.29549499996938,
              0.0,
              0.0,
              0.0,
              140.0010000000475,
              0.0,
              0.0,
              0.0,
              13.700000000000001
            ]
          },
          "uri": "7/88/90.glb"
        }
      },
      {
        "boundingVolume": {
          "box": [
            0.0,
            -2.208405000041239,
            10.25000019,
            276.0820300000487,
            0.0,
            0.0,
            0.0,
            188.84902500000317,
            0.0,
            0.0,
            0.0,
            10.149999809999999
          ]
        },
        "geometricError": 10.0,
        "refine": "REPLACE",
        "transform": [
          0.9999999989055386,
          -1.7759378983406293e-05,
          4.328426460109558e-05,
          0.0,
          1.7760647638004334e-05,
          0.9999999994127525,
          -2.9309625873941147e-05,
          0.0,
          -4.328374405493385e-05,
          2.9310394598469625e-05,
          0.9999999986337091,
          0.0,
          -275.9356857892126,
          186.85499627841637,
          -0.4505299455486238,
          1.0
        ],
        "content": {
          "boundingVolume": {
            "box": [
              -193.6820300000254,
              -183.58290000003763,
              10.25000019,
              17.945500000030734,
              0.0,
              0.0,
              0.0,
              7.47453000000678,
              0.0,
              0.0,
              0.0,
              10.149999809999999
            ]
          },
          "uri": "7/88/91.glb"
        }
      }
    ]
  }
}