{
  "asset": {
    "version": "1.1"
  },
  "geometricError": 30.0,
  "root": {
    "boundingVolume": {
      "box": [
        -4.832419999991544,
        3.588255000067875,
        51.5,
        556.9964799999725,
        0.0,
        0.0,
        0.0,
        376.86950500000967,
        0.0,
        0.0,
        0.0,
        55.900000000000006
      ]
    },
    "geometricError": 30.0,
    "refine": "REPLACE",
    "content": {
      "boundingVolume": {
        "box": [
          -88.20241499994881,
          8.037830000044778,
          51.5,
          473.62648499995703,
          0.0,
          0.0,
          0.0,
          372.41993000003276,
          0.0,
          0.0,
          0.0,
          55.900000000000006
        ]
      },
      "uri": "6/47/40.glb"
    },
    "children": [
      {
        "boundingVolume": {
          "box": [
            -4.832444999949075,
            0.0,
            46.3,
            280.91447499999776,
            0.0,
            0.0,
            0.0,
            186.64061999996193,
            0.0,
            0.0,
            0.0,
            50.7
          ]
        },
        "geometricError": 10.0,
        "refine": "REPLACE",
        "transform": [
          0.9999999989034973,
          -1.7750540452721175e-05,
          4.3335016254753e-05,
          0.0,
          1.7749273593159476e-05,
          0.9999999994151598,
          2.9234297046987212e-05,
          0.0,
          -4.333553515406541e-05,
          -2.9233527849892305e-05,
          0.9999999986337161,
          0.0,
          -276.2662769961171,
          -186.36525137722492,
          0.4314146002288908,
          1.0
        ],
        "content": {
          "boundingVolume": {
            "box": [
              -98.46591300005093,
              -14.798545000026934,
              46.3,
              187.28100699995412,
              0.0,
              0.0,
              0.0,
              162.9429249999812,
              0.0,
              0.0,
              0.0,
              50.7
            ]
          },
          "uri": "7/94/80.glb"
        }
      },
      {
        "boundingVolume": {
          "box": [
            0.0,
            3.5882500000298023,
            100.30000000000001,
            276.0820300000487,
            0.0,
            0.0,
            0.0,
            190.22886999999173,
            0.0,
            0.0,
            0.0,
            7.100000000000001
          ]
        },
        "geometricError": 10.0,
        "refine": "REPLACE",
        "transform": [
          0.9999999989034447,
          1.775096703621193e-05,
          -4.333605768791493e-05,
          0.0,
          -1.775223387737168e-05,
          0.9999999994151523,
          -2.9232750059560164e-05,
          0.0,
          4.333553875285334e-05,
          2.9233519339311176e-05,
          0.9999999986337162,
          0.0,
          276.2662617932074,
          186.36517138965428,
          -0.44884920166805387,
          1.0
        ],
        "content": {
          "boundingVolume": {
            "box": [
              97.0020300000906,
              155.38262500008568,
              100.30000000000001,
              12.340000000025611,
              0.0,
              0.0,
              0.0,
              38.43449499999406,
              0.0,
              0.0,
              0.0,
              7.100000000000001
            ]
          },
          "uri": "7/95/81.glb"
        }
      }
    ]
  }
}