{
  "asset": {
    "version": "1.1"
  },
  "geometricError": 30.0,
  "root": {
    "boundingVolume": {
      "box": [
        10.676149999955669,
        -23.329894999973476,
        20.5,
        562.8402099999948,
        0.0,
        0.0,
        0.0,
        396.6111449999735,
        0.0,
        0.0,
        0.0,
        29.200000000000003
      ]
    },
    "geometricError": 30.0,
    "refine": "REPLACE",
    "content": {
      "boundingVolume": {
        "box": [
          236.17765500000678,
          -32.588899999973364,
          20.5,
          337.33870500000194,
          0.0,
          0.0,
          0.0,
          387.3521399999736,
          0.0,
          0.0,
          0.0,
          29.200000000000003
        ]
      },
      "uri": "6/37/15.glb"
    },
    "children": [
      {
        "boundingVolume": {
          "box": [
            10.676149999955669,
            -23.32990000001155,
            21.7,
            286.75818000000436,
            0.0,
            0.0,
            0.0,
            209.97051999997348,
            0.0,
            0.0,
            0.0,
            25.7
          ]
        },
        "geometricError": 10.0,
        "refine": "REPLACE",
        "transform": [
          0.9999999989079966,
          1.7587445676842117e-05,
          -4.329766715788219e-05,
          0.0,
          -1.7586177532724623e-05,
          0.9999999994164354,
          2.92891763386538e-05,
          0.0,
          4.3298182254458695e-05,
          -2.9288414866046608e-05,
          0.9999999986337279,
          0.0,
          276.03005236480385,
          -186.71644554683007,
          0.42962037422694266,
          1.0
        ],
        "content": {
          "boundingVolume": {
            "box": [
              136.6513050000649,
              -72.16027499991469,
              21.7,
              160.78302499995334,
              0.0,
              0.0,
              0.0,
              161.14014500001213,
              0.0,
              0.0,
              0.0,
              25.7
            ]
          },
          "uri": "7/75/30.glb"
        }
      },
      {
        "boundingVolume": {
          "box": [
            0.0,
            0.0,
            42.85,
            276.0820300000487,
            0.0,
            0.0,
            0.0,
            186.64061999996193,
            0.0,
            0.0,
            0.0,
            6.850000000000001
          ]
        },
        "geometricError": 10.0,
        "refine": "REPLACE",
        "transform": [
          0.9999999989079444,
          -1.7587866866453084e-05,
          4.3298704063943205e-05,
          0.0,
          1.758913499280701e-05,
          0.9999999994164278,
          -2.92876525540553e-05,
          0.0,
          -4.329818893145099e-05,
          2.9288414108874505e-05,
          0.9999999986337278,
          0.0,
          -276.03005697298795,
          186.71641504298896,
          -0.447055495576933,
          1.0
        ],
        "content": {
          "boundingVolume": {
            "box": [
              177.27537499996834,
              43.39236450009048,
              42.85,
              2.3543850000132807,
              0.0,
              0.0,
              0.0,
              2.4182584999944083,
              0.0,
              0.0,
              0.0,
              6.850000000000001
            ]
          },
          "uri": "7/74/31.glb"
        }
      },
      {
        "boundingVolume": {
          "box": [
            0.0,
            0.0,
            16.950000000000003,
            276.0820300000487,
            0.0,
            0.0,
            0.0,
            186.64061999996193,
            0.0,
            0.0,
            0.0,
            25.65
          ]
        },
        "geometricError": 10.0,
        "refine": "REPLACE",
        "transform": [
          0.999999998907126,
          1.7594456622332943e-05,
          -4.3314927059723285e-05,
          0.0,
          -1.7595724184249484e-05,
          0.9999999994170146,
          -2.926365180749846e-05,
          0.0,
          4.33144121563811e-05,
          2.9264413933194344e-05,
          0.9999999986337278,
          0.0,
          276.13348158448935,
          186.5634116588626,
          -0.4466962767764926,
          1.0
        ],
        "content": {
          "boundingVolume": {
            "box": [
              110.72878100001253,
              60.5601214999333,
              16.950000000000003,
              84.40849900001194,
              0.0,
              0.0,
              0.0,
              107.56249850004679,
              0.0,
              0.0,
              0.0,
              25.65
            ]
          },
          "uri": "7/75/31.glb"
        }
      }
    ]
  }
}