{
  "asset": {
    "version": "1.1"
  },
  "geometricError": 30.0,
  "root": {
    "boundingVolume": {
      "box": [
        -13.514119999948889,
        -14.101750000030734,
        84.1,
        565.6781799999881,
        0.0,
        0.0,
        0.0,
        407.91934999998193,
        0.0,
        0.0,
        0.0,
        89.5
      ]
    },
    "geometricError": 30.0,
    "refine": "REPLACE",
    "content": {
      "boundingVolume": {
        "box": [
          -39.8332249999512,
          -14.101750000030734,
          84.1,
          539.3590749999858,
          0.0,
          0.0,
          0.0,
          407.91934999998193,
          0.0,
          0.0,
          0.0,
          89.5
        ]
      },
      "uri": "6/37/27.glb"
    },
    "children": [
      {
        "boundingVolume": {
          "box": [
            -13.552034999942407,
            0.7321999999694526,
            70.45,
            289.6340650000493,
            0.0,
            0.0,
            0.0,
            236.1126800000202,
            0.0,
            0.0,
            0.0,
            75.85000000000001
          ]
        },
        "geometricError": 10.0,
        "refine": "REPLACE",
        "transform": [
          0.9999999989059186,
          -1.766505838216026e-05,
          4.3314065904631605e-05,
          0.0,
          1.7663790794930634e-05,
          0.9999999994157681,
          2.926523356100441e-05,
          0.0,
          -4.331458285133927e-05,
          -2.926446843826147e-05,
          0.9999999986337189,
          0.0,
          -276.13369549112394,
          -186.56316844094545,
          0.4305211855098605,
          1.0
        ],
        "content": {
          "boundingVolume": {
            "box": [
              -47.69987500004936,
              0.7321999999694526,
              70.45,
              255.48622500000056,
              0.0,
              0.0,
              0.0,
              236.1126800000202,
              0.0,
              0.0,
              0.0,
              75.85000000000001
            ]
          },
          "uri": "7/74/54.glb"
        }
      },
      {
        "boundingVolume": {
          "box": [
            -14.464884999906644,
            -7.819230000022799,
            97.95,
            290.54691500001354,
            0.0,
            0.0,
            0.0,
            207.2209000000148,
            0.0,
            0.0,
            0.0,
            63.05
          ]
        },
        "geometricError": 10.0,
        "refine": "REPLACE",
        "transform": [
          0.9999999989067414,
          1.7658415534832494e-05,
          -4.329777789008338e-05,
          0.0,
          -1.7657147381194838e-05,
          0.9999999994151803,
          2.928932336021539e-05,
          0.0,
          4.329829506782845e-05,
          -2.9288558812845533e-05,
          0.9999999986337191,
          0.0,
          276.0298596727662,
          -186.71674638567492,
          0.4308827391359955,
          1.0
        ],
        "content": {
          "boundingVolume": {
            "box": [
              -45.3636749999132,
              -7.819230000022799,
              97.95,
              259.648125000007,
              0.0,
              0.0,
              0.0,
              207.2209000000148,
              0.0,
              0.0,
              0.0,
              63.05
            ]
          },
          "uri": "7/75/54.glb"
        }
      },
      {
        "boundingVolume": {
          "box": [
            -4.674944999977015,
            4.451415000017732,
            56.75,
            280.7569750000257,
            0.0,
            0.0,
            0.0,
            202.7255550000118,
            0.0,
            0.0,
            0.0,
            61.849999999999994
          ]
        },
        "geometricError": 10.0,
        "refine": "REPLACE",
        "transform": [
          0.9999999989066888,
          -1.7658840127332542e-05,
          4.329881897519039e-05,
          0.0,
          1.766010826320663e-05,
          0.9999999994151726,
          -2.9287793419374708e-05,
          0.0,
          -4.329830176136307e-05,
          2.9288558049178626e-05,
          0.9999999986337187,
          0.0,
          -276.02986427629367,
          186.7167157670483,
          -0.4483177687507123,
          1.0
        ],
        "content": {
          "boundingVolume": {
            "box": [
              -4.924869999988005,
              4.451415000017732,
              56.75,
              280.5070500000147,
              0.0,
              0.0,
              0.0,
              202.7255550000118,
              0.0,
              0.0,
              0.0,
              61.849999999999994
            ]
          },
          "uri": "7/74/55.glb"
        }
      },
      {
        "boundingVolume": {
          "box": [
            0.0,
            -8.434374999953434,
            86.05,
            276.0820300000487,
            0.0,
            0.0,
            0.0,
            195.07499499997357,
            0.0,
            0.0,
            0.0,
            87.55
          ]
        },
        "geometricError": 10.0,
        "refine": "REPLACE",
        "transform": [
          0.9999999989058662,
          1.7665482242468222e-05,
          -4.331510519428594e-05,
          0.0,
          -1.7666749811656723e-05,
          0.9999999994157607,
          -2.926369914552085e-05,
          0.0,
          4.3314588211662564e-05,
          2.926446435069785e-05,
          0.9999999986337187,
          0.0,
          276.1336916126311,
          186.5631166745443,
          -0.447956113377586,
          1.0
        ],
        "content": {
          "boundingVolume": {
            "box": [
              -25.10323500004597,
              -11.276319999946281,
              86.05,
              248.54706499999156,
              0.0,
              0.0,
              0.0,
              192.23304999998072,
              0.0,
              0.0,
              0.0,
              87.55
            ]
          },
          "uri": "7/75/55.glb"
        }
      }
    ]
  }
}