{
  "asset": {
    "version": "1.1"
  },
  "geometricError": 30.0,
  "root": {
    "boundingVolume": {
      "box": [
        0.0,
        -3.0537550000008196,
        257.9,
        552.164059999981,
        0.0,
        0.0,
        0.0,
        376.3350050000008,
        0.0,
        0.0,
        0.0,
        37.900000000000006
      ]
    },
    "geometricError": 30.0,
    "refine": "REPLACE",
    "content": {
      "boundingVolume": {
        "box": [
          183.30668499995954,
          -325.64526000001933,
          257.9,
          327.9864950000192,
          0.0,
          0.0,
          0.0,
          53.743499999982305,
          0.0,
          0.0,
          0.0,
          37.900000000000006
        ]
      },
      "uri": "6/6/17.glb"
    },
    "children": [
      {
        "boundingVolume": {
          "box": [
            0.0,
            -2.705255000037141,
            247.6,
            276.0820300000487,
            0.0,
            0.0,
            0.0,
            189.34587499999907,
            0.0,
            0.0,
            0.0,
            27.599999999999994
          ]
        },
        "geometricError": 10.0,
        "refine": "REPLACE",
        "transform": [
          0.9999999989102423,
          -1.7579293317943057e-05,
          4.3249089412444874e-05,
          0.0,
          1.7578023538661336e-05,
          0.9999999994145053,
          2.935988182195537e-05,
          0.0,
          -4.3249605513218103e-05,
          -2.935912155643816e-05,
          0.9999999986337569,
          0.0,
          -275.7202222645283,
          -187.16710649663582,
          0.4308855275157839,
          1.0
        ],
        "content": {
          "boundingVolume": {
            "box": [
              203.53885000001173,
              -138.6561249999795,
              247.6,
              72.1366299999645,
              0.0,
              0.0,
              0.0,
              53.39500499999849,
              0.0,
              0.0,
              0.0,
              27.599999999999994
            ]
          },
          "uri": "7/12/34.glb"
        }
      },
      {
        "boundingVolume": {
          "box": [
            0.0,
            -3.053749999962747,
            263.6,
            276.0820300000487,
            0.0,
            0.0,
            0.0,
            189.69436999998288,
            0.0,
            0.0,
            0.0,
            32.2
          ]
        },
        "geometricError": 10.0,
        "refine": "REPLACE",
        "transform": [
          0.9999999989045747,
          1.7624948149108643e-05,
          -4.336141075783617e-05,
          0.0,
          -1.7623682275508257e-05,
          0.9999999994185653,
          2.9193760012202752e-05,
          0.0,
          4.336192527104599e-05,
          -2.9192995792404197e-05,
          0.9999999986337562,
          0.0,
          276.4362709671259,
          -186.1080393642187,
          0.42839825013652444,
          1.0
        ],
        "content": {
          "boundingVolume": {
            "box": [
              1.655655000009574,
              -164.53512499993667,
              263.6,
              233.5554949999787,
              0.0,
              0.0,
              0.0,
              28.21299500000896,
              0.0,
              0.0,
              0.0,
              32.2
            ]
          },
          "uri": "7/13/34.glb"
        }
      }
    ]
  }
}