{
  "asset": {
    "version": "1.1"
  },
  "geometricError": 30.0,
  "root": {
    "boundingVolume": {
      "box": [
        0.07129999995231628,
        44.00858999998309,
        29.5,
        588.7094999999972,
        0.0,
        0.0,
        0.0,
        419.123339999991,
        0.0,
        0.0,
        0.0,
        33.6
      ]
    },
    "geometricError": 30.0,
    "refine": "REPLACE",
    "content": {
      "boundingVolume": {
        "box": [
          0.07129999995231628,
          44.00858999998309,
          29.5,
          588.7094999999972,
          0.0,
          0.0,
          0.0,
          419.123339999991,
          0.0,
          0.0,
          0.0,
          33.6
        ]
      },
      "uri": "6/41/35.glb"
    },
    "children": [
      {
        "boundingVolume": {
          "box": [
            -18.237059999955818,
            4.494380000047386,
            24.7000001,
            294.3190900000045,
            0.0,
            0.0,
            0.0,
            192.96850000001723,
            0.0,
            0.0,
            0.0,
            28.3999999
          ]
        },
        "geometricError": 10.0,
        "refine": "REPLACE",
        "transform": [
          0.9999999989046554,
          -1.771583528292764e-05,
          4.3322491100228344e-05,
          0.0,
          1.7714567983273533e-05,
          0.9999999994152309,
          2.9252904435894678e-05,
          0.0,
          -4.3323009314477634e-05,
          -2.925213696453044e-05,
          0.9999999986337145,
          0.0,
          -276.1868052757345,
          -186.48414280451834,
          0.4311730151530355,
          1.0
        ],
        "content": {
          "boundingVolume": {
            "box": [
              -19.404159999918193,
              4.494380000047386,
              24.7000001,
              293.1519899999839,
              0.0,
              0.0,
              0.0,
              192.96850000001723,
              0.0,
              0.0,
              0.0,
              28.3999999
            ]
          },
          "uri": "7/82/70.glb"
        }
      },
      {
        "boundingVolume": {
          "box": [
            0.0,
            4.240334999980405,
            24.5,
            276.0820300000487,
            0.0,
            0.0,
            0.0,
            192.5285450000083,
            0.0,
            0.0,
            0.0,
            23.0
          ]
        },
        "geometricError": 10.0,
        "refine": "REPLACE",
        "transform": [
          0.9999999989063246,
          1.7702332958918765e-05,
          -4.328947237414171e-05,
          0.0,
          -1.7701064511127518e-05,
          0.99999999941404,
          2.9301738758813478e-05,
          0.0,
          4.328999105795983e-05,
          -2.9300972457013685e-05,
          0.9999999986337149,
          0.0,
          275.97631192486733,
          -186.79547204519622,
          0.4319073457736522,
          1.0
        ],
        "content": {
          "boundingVolume": {
            "box": [
              -1.3792200000025332,
              4.240334999980405,
              24.5,
              250.071009999956,
              0.0,
              0.0,
              0.0,
              192.5285450000083,
              0.0,
              0.0,
              0.0,
              23.0
            ]
          },
          "uri": "7/83/70.glb"
        }
      },
      {
        "boundingVolume": {
          "box": [
            50.98331000003964,
            41.43046499998309,
            29.65,
            327.0653400000301,
            0.0,
            0.0,
            0.0,
            235.06083500001114,
            0.0,
            0.0,
            0.0,
            24.65
          ]
        },
        "geometricError": 10.0,
        "refine": "REPLACE",
        "transform": [
          0.9999999989062718,
          -1.770276021520467e-05,
          4.329051719120791e-05,
          0.0,
          1.7704028645260106e-05,
          0.9999999994140327,
          -2.9300207071703e-05,
          0.0,
          -4.3289998471252034e-05,
          2.930097345626992e-05,
          0.9999999986337145,
          0.0,
          -275.9763210359961,
          186.7954525940586,
          -0.44934233999811113,
          1.0
        ],
        "content": {
          "boundingVolume": {
            "box": [
              59.36674500000663,
              41.43046499998309,
              29.65,
              318.6819050000049,
              0.0,
              0.0,
              0.0,
              235.06083500001114,
              0.0,
              0.0,
              0.0,
              24.65
            ]
          },
          "uri": "7/82/71.glb"
        }
      },
      {
        "boundingVolume": {
          "box": [
            18.58638500003144,
            10.59254499990493,
            29.5,
            294.6684150000219,
            0.0,
            0.0,
            0.0,
            202.98808500001905,
            0.0,
            0.0,
            0.0,
            33.6
          ]
        },
        "geometricError": 10.0,
        "refine": "REPLACE",
        "transform": [
          0.9999999989046028,
          1.771626102919921e-05,
          -4.332353222463725e-05,
          0.0,
          -1.771752831070117e-05,
          0.9999999994152236,
          -2.925136355202973e-05,
          0.0,
          4.332301397458327e-05,
          2.925213110599456e-05,
          0.9999999986337147,
          0.0,
          276.18679686961696,
          186.4840797202196,
          -0.44860780145972967,
          1.0
        ],
        "content": {
          "boundingVolume": {
            "box": [
              26.430285000009462,
              10.59254499990493,
              29.5,
              286.8245149999857,
              0.0,
              0.0,
              0.0,
              202.98808500001905,
              0.0,
              0.0,
              0.0,
              33.6
            ]
          },
          "uri": "7/83/71.glb"
        }
      }
    ]
  }
}